{
  "index": 185,
  "name": "Sura 185",
  "ayas": [
    {
      "index": 1,
      "text": "lā ilāha illallāh",
      "bismillah": ""
    },
    {
      "index": 2,
      "text": "waḥdahu lā sharīka lah"
    },
    {
      "index": 3,
      "text": "lahul mulku walahul ḥamd"
    },
    {
      "index": 4,
      "text": "yuḥyī wayumīt"
    },
    {
      "index": 5,
      "text": "wayumītu wayuḥyī"
    },
    {
      "index": 6,
      "text": "wahuwa ḥayyun lā yamūt"
    },
    {
      "index": 7,
      "text": "biyadihil khayr"
    },
    {
      "index": 8,
      "text": "wahuwa `alā kulli shay-in qadīr"
    },
    {
      "index": 9,
      "text": ""
    },
    {
      "index": 10,
      "text": "lā ilāha illallāh"
    },
    {
      "index": 11,
      "text": "waḥdahu lā sharīka lah"
    },
    {
      "index": 12,
      "text": "lahul mulku walahul ḥamd"
    },
    {
      "index": 13,
      "text": "yuḥyī wayumīt"
    },
    {
      "index": 14,
      "text": "wayumītu wayuḥyī"
    },
    {
      "index": 15,
      "text": "wahuwa ḥayyun lā yamūt"
    },
    {
      "index": 16,
      "text": "biyadihil khayr"
    },
    {
      "index": 17,
      "text": "wahuwa `alā kulli shay-in qadīr"
    },
    {
      "index": 18,
      "text": ""
    },
    {
      "index": 19,
      "text": "lā ilāha illallāh"
    },
    {
      "index": 20,
      "text": "waḥdahu lā sharīka lah"
    },
    {
      "index": 21,
      "text": "lahul mulku walahul ḥamd"
    },
    {
      "index": 22,
      "text": "yuḥyī wayumīt"
    },
    {
      "index": 23,
      "text": "wayumītu wayuḥyī"
    },
    {
      "index": 24,
      "text": "wahuwa ḥayyun lā yamūt"
    },
    {
      "index": 25,
      "text": "biyadihil khayr"
    },
    {
      "index": 26,
      "text": "wahuwa `alā kulli shay-in qadīr"
    },
    {
      "index": 27,
      "text": ""
    },
    {
      "index": 28,
      "text": "lā ilāha illallāh"
    },
    {
      "index": 29,
      "text": "waḥdahu lā sharīka lah"
    },
    {
      "index": 30,
      "text": "lahul mulku walahul ḥamd"
    },
    {
      "index": 31,
      "text": "yuḥyī wayumīt"
    },
    {
      "index": 32,
      "text": "wayumītu wayuḥyī"
    },
    {
      "index": 33,
      "text": "wahuwa ḥayyun lā yamūt"
    },
    {
      "index": 34,
      "text": "biyadihil khayr"
    },
    {
      "index": 35,
      "text": "wahuwa `alā kulli shay-in qadīr"
    },
    {
      "index": 36,
      "text": ""
    },
    {
      "index": 37,
      "text": "lā ilāha illallāh"
    },
    {
      "index": 38,
      "text": "waḥdahu lā sharīka lah"
    },
    {
      "index": 39,
      "text": "lahul mulku walahul ḥamd"
    },
    {
      "index": 40,
      "text": "yuḥyī wayumīt"
    },
    {
      "index": 41,
      "text": "wayumītu wayuḥyī"
    },
    {
      "index": 42,
      "text": "wahuwa ḥayyun lā yamūt"
    },
    {
      "index": 43,
      "text": "biyadihil khayr"
    },
    {
      "index": 44,
      "text": "wahuwa `alā kulli shay-in qadīr"
    },
    {
      "index": 45,
      "text": ""
    },
    {
      "index": 46,
      "text": "lā ilāha illallāh"
    },
    {
      "index": 47,
      "text": "waḥdahu lā sharīka lah"
    },
    {
      "index": 48,
      "text": "lahul mulku walahul ḥamd"
    },
    {
      "index": 49,
      "text": "yuḥyī wayumīt"
    },
    {
      "index": 50,
      "text": "wayumītu wayuḥyī"
    },
    {
      "index": 51,
      "text": "wahuwa ḥayyun lā yamūt"
    },
    {
      "index": 52,
      "text": "biyadihil khayr"
    },
    {
      "index": 53,
      "text": "wahuwa `alā kulli shay-in qadīr"
    },
    {
      "index": 54,
      "text": ""
    },
    {
      "index": 55,
      "text": "lā ilāha illallāh"
    },
    {
      "index": 56,
      "text": "waḥdahu lā sharīka lah"
    },
    {
      "index": 57,
      "text": "lahul mulku walahul ḥamd"
    },
    {
      "index": 58,
      "text": "yuḥyī wayumīt"
    },
    {
      "index": 59,
      "text": "wayumītu wayuḥyī"
    },
    {
      "index": 60,
      "text": "wahuwa ḥayyun lā yamūt"
    },
    {
      "index": 61,
      "text": "biyadihil khayr"
    },
    {
      "index": 62,
      "text": "wahuwa `alā kulli shay-in qadīr"
    },
    {
      "index": 63,
      "text": ""
    },
    {
      "index": 64,
      "text": "lā ilāha illallāh"
    },
    {
      "index": 65,
      "text": "waḥdahu lā sharīka lah"
    },
    {
      "index": 66,
      "text": "lahul mulku walahul ḥamd"
    },
    {
      "index": 67,
      "text": "yuḥyī wayumīt"
    },
    {
      "index": 68,
      "text": "wayumītu wayuḥyī"
    },
    {
      "index": 69,
      "text": "wahuwa ḥayyun lā yamūt"
    },
    {
      "index": 70,
      "text": "biyadihil khayr"
    },
    {
      "index": 71,
      "text": "wahuwa `alā kulli shay-in qadīr"
    },
    {
      "index": 72,
      "text": ""
    },
    {
      "index": 73,
      "text": "lā ilāha illallāh"
    },
    {
      "index": 74,
      "text": "waḥdahu lā sharīka lah"
    },
    {
      "index": 75,
      "text": "lahul mulku walahul ḥamd"
    },
    {
      "index": 76,
      "text": "yuḥyī wayumīt"
    },
    {
      "index": 77,
      "text": "wayumītu wayuḥyī"
    },
    {
      "index": 78,
      "text": "wahuwa ḥayyun lā yamūt"
    },
    {
      "index": 79,
      "text": "biyadihil khayr"
    },
    {
      "index": 80,
      "text": "wahuwa `alā kulli shay-in qadīr"
    },
    {
      "index": 81,
      "text": ""
    },
    {
      "index": 82,
      "text": "la-ilāha illallāh"
    },
    {
      "index": 83,
      "text": "waḥdahu lāsharīka lah"
    },
    {
      "index": 84,
      "text": "lahul mulk, walahul ḥamd"
    },
    {
      "index": 85,
      "text": "yuḥyī wayumīt"
    },
    {
      "index": 86,
      "text": "wayumītu wayuḥyī"
    },
    {
      "index": 87,
      "text": "wahuwa ḥayyun lāyamūt"
    },
    {
      "index": 88,
      "text": "biyadihil khayr"
    },
    {
      "index": 89,
      "text": "wahuwa `alā kulli shay-in qadīr"
    }
  ]
}